atlasai/vinz/client/.env
atlasai/vinz/client/__init__.py
atlasai/vinz/client/authenticate.py
atlasai/vinz/client/utils.py
atlasai_vinz_client-0.0.2.dist-info/METADATA
atlasai_vinz_client-0.0.2.dist-info/WHEEL
atlasai_vinz_client-0.0.2.dist-info/top_level.txt
atlasai_vinz_client-0.0.2.dist-info/RECORD
